cubicweb_fds/__init__.py
cubicweb_fds/__pkginfo__.py
cubicweb_fds/site_cubicweb.py
cubicweb_fds/uiprops.py
cubicweb_fds/data/ajax-loader.gif
cubicweb_fds/data/cubes.bootstrap.css
cubicweb_fds/data/cubes.bootstrap.cw_compat.css
cubicweb_fds/data/cubes.bootstrap.edition.js
cubicweb_fds/data/cubes.bootstrap.js
cubicweb_fds/data/cubes.squareui.js
cubicweb_fds/data/cubicweb.form.css
cubicweb_fds/data/cubicweb.tableview.css
cubicweb_fds/data/go_next.png
cubicweb_fds/data/go_prev.png
cubicweb_fds/data/logo-cubicweb.svg
cubicweb_fds/data/pen_icon.png
cubicweb_fds/data/required.png
cubicweb_fds/data/css/bootstrap-theme.css
cubicweb_fds/data/css/bootstrap-theme.min.css
cubicweb_fds/data/css/bootstrap.min.css
cubicweb_fds/data/css/fluid-design-system.css
cubicweb_fds/data/css/reboot.css
cubicweb_fds/data/css/components/alert/index.css
cubicweb_fds/data/css/components/alert/index.d.ts
cubicweb_fds/data/css/components/alert/index.js
cubicweb_fds/data/css/components/avatar/index.css
cubicweb_fds/data/css/components/badge/index.css
cubicweb_fds/data/css/components/breadcrumb/index.css
cubicweb_fds/data/css/components/button/index.css
cubicweb_fds/data/css/components/card/index.css
cubicweb_fds/data/css/components/checkbox/index.css
cubicweb_fds/data/css/components/checkbox/index.d.ts
cubicweb_fds/data/css/components/checkbox/index.js
cubicweb_fds/data/css/components/collapse/index.css
cubicweb_fds/data/css/components/collapse/index.d.ts
cubicweb_fds/data/css/components/collapse/index.js
cubicweb_fds/data/css/components/dropdown/index.css
cubicweb_fds/data/css/components/dropdown/index.d.ts
cubicweb_fds/data/css/components/dropdown/index.js
cubicweb_fds/data/css/components/fab/index.css
cubicweb_fds/data/css/components/fab/index.d.ts
cubicweb_fds/data/css/components/fab/index.js
cubicweb_fds/data/css/components/footer/index.css
cubicweb_fds/data/css/components/form/autocomplete.d.ts
cubicweb_fds/data/css/components/form/index.css
cubicweb_fds/data/css/components/form/index.d.ts
cubicweb_fds-1.6.5.dist-info/METADATA
cubicweb_fds-1.6.5.dist-info/WHEEL
cubicweb_fds-1.6.5.dist-info/entry_points.txt
cubicweb_fds-1.6.5.dist-info/top_level.txt
cubicweb_fds-1.6.5.dist-info/RECORD
