Metadata-Version: 2.1
Name: cubicweb-fds
Version: 1.6.5
Summary: UNKNOWN
Home-page: https://www.cubicweb.org/project/cubicweb-fds
Author: LOGILAB S.A. (Paris, FRANCE)
Author-email: contact@logilab.fr
License: LGPL
Platform: UNKNOWN
Classifier: Environment :: Web Environment
Classifier: Framework :: CubicWeb
Classifier: Programming Language :: Python
Classifier: Programming Language :: Python :: 2
Classifier: Programming Language :: Python :: 3
Classifier: Programming Language :: JavaScript
Requires-Python: >=2.7
Requires-Dist: cubicweb (>=3.26.0)
Requires-Dist: six (>=1.12.O)
